pycognito/__init__.py
pycognito/aws_srp.py
pycognito/exceptions.py
pycognito/utils.py
pycognito-2024.5.1.dist-info/LICENSE
pycognito-2024.5.1.dist-info/METADATA
pycognito-2024.5.1.dist-info/WHEEL
pycognito-2024.5.1.dist-info/top_level.txt
pycognito-2024.5.1.dist-info/zip-safe
pycognito-2024.5.1.dist-info/RECORD
