Metadata-Version: 2.1
Name: pycognito
Version: 2024.5.1
Summary: Python class to integrate Boto3's Cognito client so it is easy to login users. With SRP support.
Home-page: https://github.com/pvizeli/pycognito
Download-URL: https://github.com/pvizeli/pycognito/tarball/2024.5.1
Author: Pascal Vizeli
Author-email: pvizeli@syshack.ch
License: Apache License 2.0
Keywords: aws,cognito,api,gateway,serverless
Classifier: Programming Language :: Python :: 3.8
Classifier: Programming Language :: Python :: 3.9
Classifier: Programming Language :: Python :: 3.10
Classifier: Programming Language :: Python :: 3.11
Classifier: Programming Language :: Python :: 3.12
Classifier: Topic :: Software Development :: Libraries :: Python Modules
Classifier: Environment :: Web Environment
Requires-Python: >=3.8
License-File: LICENSE
Requires-Dist: boto3>=1.10.49
Requires-Dist: envs>=1.3
Requires-Dist: pyjwt[crypto]>=2.8.0
Requires-Dist: requests>=2.22.0
